phal_plugin_save_conversations/__init__.py
phal_plugin_save_conversations-0.2.1.dist-info/LICENSE
phal_plugin_save_conversations-0.2.1.dist-info/METADATA
phal_plugin_save_conversations-0.2.1.dist-info/WHEEL
phal_plugin_save_conversations-0.2.1.dist-info/entry_points.txt
phal_plugin_save_conversations-0.2.1.dist-info/top_level.txt
phal_plugin_save_conversations-0.2.1.dist-info/RECORD
